LICENSE
README.md
setup.cfg
setup.py
distsim/__init__.py
distsim/link.py
distsim/message.py
distsim/network.py
distsim/node.py
distsim.egg-info/PKG-INFO
distsim.egg-info/SOURCES.txt
distsim.egg-info/dependency_links.txt
distsim.egg-info/not-zip-safe
distsim.egg-info/requires.txt
distsim.egg-info/top_level.txt