Metadata-Version: 2.1
Name: distsim
Version: 0.3.0
Summary: Simulator of distributed system
Home-page: https://github.com/mikulatomas/distsim
Author: Tomáš Mikula
Author-email: mail@tomasmikula.cz
License: MIT license
Keywords: distributed system simulator simple education parallelism
Platform: UNKNOWN
Classifier: Development Status :: 2 - Pre-Alpha
Classifier: Intended Audience :: Developers
Classifier: License :: OSI Approved :: MIT License
Classifier: Natural Language :: English
Classifier: Programming Language :: Python :: 3
Classifier: Programming Language :: Python :: 3.6
Classifier: Programming Language :: Python :: 3.7
Classifier: Programming Language :: Python :: 3.8
Classifier: Programming Language :: Python :: 3.9
Classifier: Programming Language :: Python :: 3.10
Requires-Python: >=3.6
Provides-Extra: docs
License-File: LICENSE
